CHANGES.rst
MANIFEST.in
README.rst
setup.cfg
setup.py
khufu_script/__init__.py
khufu_script/db.py
khufu_script/shell.py
khufu_script/tests.py
khufu_script/utils.py
khufu_script/wsgi.py
khufu_script.egg-info/PKG-INFO
khufu_script.egg-info/SOURCES.txt
khufu_script.egg-info/dependency_links.txt
khufu_script.egg-info/not-zip-safe
khufu_script.egg-info/requires.txt
khufu_script.egg-info/top_level.txt