Metadata-Version: 1.0
Name: khufu-script
Version: 0.6.2
Summary: Manage script support for Khufu/Pyramid apps
Home-page: https://github.com/khufuproject/khufu_script
Author: Rocky Burt
Author-email: rocky@serverzen.com
License: BSD
Keywords: pyramid khufu clue_script manage script syncdb loaddata
Platform: UNKNOWN
Classifier: License :: OSI Approved :: BSD License
Classifier: Programming Language :: Python
Classifier: Topic :: Internet :: WWW/HTTP :: WSGI
